MANIFEST.in
README.rst
setup.py
client/__init__.py
client/client.py
client/cowry.conf.default
client/requirements.txt
client/core/__init__.py
client/core/action.py
client/core/baseSocket.py
client/core/config.py
client/core/cryptogram.py
client/core/download.py
client/core/ftpClient.py
client/core/sslSetting.py
client/core/syslog.py
client/core/upload.py
client/core/utils.py
client/resources/__init__.py
client/resources/certinfo.py
client/resources/closefile.py
client/resources/download.py
client/resources/icon_rc.py
client/resources/mainwindow.py
client/resources/openfile.py
client/resources/transferfile.py
client/resources/upload.py
cowry.egg-info/PKG-INFO
cowry.egg-info/SOURCES.txt
cowry.egg-info/dependency_links.txt
cowry.egg-info/entry_points.txt
cowry.egg-info/requires.txt
cowry.egg-info/top_level.txt
server/__init__.py
server/cowry.conf.default
server/requirements.txt
server/server.py
server/core/__init__.py
server/core/baseSocket.py
server/core/common.py
server/core/config.py
server/core/connection.py
server/core/console.py
server/core/database.py
server/core/download.py
server/core/encrypt.py
server/core/etcd_store.py
server/core/status.py
server/core/syslog.py
server/core/system.py
server/core/upload.py
server/core/utils.py
server/core/worker.py
server/core/components/__init__.py
server/core/components/cowry_admin/__init__.py
server/core/components/cowry_admin/admin_routes.py
server/core/components/cowry_admin/api.py
server/core/components/cowry_admin/cowry_admin.py
server/core/components/cowry_admin/gunicorn_runner.py
server/core/components/cowry_admin/routes.py
server/core/components/cowry_admin/service.py
server/core/components/cowry_admin/user_routes.py
server/core/components/cowry_admin/utils.py
server/core/components/cowry_admin/static/css/bootstrap-theme.css
server/core/components/cowry_admin/static/css/bootstrap-theme.css.map
server/core/components/cowry_admin/static/css/bootstrap-theme.min.css
server/core/components/cowry_admin/static/css/bootstrap-theme.min.css.map
server/core/components/cowry_admin/static/css/bootstrap.css
server/core/components/cowry_admin/static/css/bootstrap.css.map
